[{"id":"57003795-77db-4830-94a2-3b18edfdf30c","employee_id":"emp_mnuy6bg7_tuj0qu","employee_name":"Colt","customer_type":"standard","items":[{"name": "Rolling Block", "quantity": 1, "productId": "rf_9", "unitPrice": 1000, "commission": 350, "totalPrice": 1000, "discountedPrice": 1000}, {"name": "Engraving Plate", "quantity": 1, "productId": "co_5", "unitPrice": 20, "commission": 7, "totalPrice": 20, "discountedPrice": 20}],"total_amount":1020.00,"total_commission":357.00,"ledger_amount":663.00,"timestamp":"2026-04-15T00:43:29.425Z","created_at":"2026-04-15T00:43:29.896293+00:00","updated_at":"2026-04-15T00:43:29.896293+00:00"}, 
 {"id":"8041491a-b947-4891-aca3-bd085c236c91","employee_id":"emp_mnuy6bg7_tuj0qu","employee_name":"Colt","customer_type":"standard","items":[{"name": "Sawn-Off", "quantity": 6, "productId": "sg_1", "unitPrice": 35, "commission": 73.5, "totalPrice": 210, "discountedPrice": 35}, {"name": "Bolt-Action", "quantity": 4, "productId": "rf_3", "unitPrice": 75, "commission": 105, "totalPrice": 300, "discountedPrice": 75}],"total_amount":510.00,"total_commission":178.50,"ledger_amount":331.50,"timestamp":"2026-04-14T23:48:36.427Z","created_at":"2026-04-14T23:48:37.214999+00:00","updated_at":"2026-04-14T23:48:37.214999+00:00"}, 
 {"id":"8c67ac65-1b59-4f22-a8ec-05ae2b8538e6","employee_id":"emp_mnuy6bg7_tuj0qu","employee_name":"Colt","customer_type":"standard","items":[{"name": "Evans", "quantity": 1, "productId": "rp_1", "unitPrice": 25, "commission": 8.75, "totalPrice": 25, "discountedPrice": 25}],"total_amount":25.00,"total_commission":8.75,"ledger_amount":16.25,"timestamp":"2026-04-14T23:08:48.106Z","created_at":"2026-04-14T23:08:48.942513+00:00","updated_at":"2026-04-14T23:08:48.942513+00:00"}, 
 {"id":"43890980-25fe-45c8-a769-591912ecdff1","employee_id":"emp_mnuy6bg7_tuj0qu","employee_name":"Colt","customer_type":"standard","items":[{"name": "LeMat", "quantity": 1, "productId": "rv_4", "unitPrice": 35, "commission": 12.25, "totalPrice": 35, "discountedPrice": 35}],"total_amount":35.00,"total_commission":12.25,"ledger_amount":22.75,"timestamp":"2026-04-14T00:36:30.242Z","created_at":"2026-04-14T00:36:30.223953+00:00","updated_at":"2026-04-14T00:36:30.223953+00:00"}, 
 {"id":"e15434d6-b1fc-4426-ae17-b91d164f37c4","employee_id":"emp_mnuy6bg7_tuj0qu","employee_name":"Colt","customer_type":"standard","items":[{"name": "Winchester", "quantity": 1, "productId": "rp_3", "unitPrice": 55, "commission": 19.25, "totalPrice": 55, "discountedPrice": 55}],"total_amount":55.00,"total_commission":19.25,"ledger_amount":35.75,"timestamp":"2026-04-14T00:33:32.269Z","created_at":"2026-04-14T00:33:32.004282+00:00","updated_at":"2026-04-14T00:33:32.004282+00:00"}, 
 {"id":"296b2af1-9e06-4726-8d98-5a6097922665","employee_id":"emp_1","employee_name":"Cat","customer_type":"standard","items":[{"name": "Bolt-Action", "quantity": 1, "productId": "rf_3", "unitPrice": 75, "commission": 26.25, "totalPrice": 75, "discountedPrice": 75}, {"name": "Navy", "quantity": 1, "productId": "rv_3", "unitPrice": 35, "commission": 12.25, "totalPrice": 35, "discountedPrice": 35}],"total_amount":110.00,"total_commission":38.50,"ledger_amount":71.50,"timestamp":"2026-04-12T22:54:42.797Z","created_at":"2026-04-12T22:56:17.049457+00:00","updated_at":"2026-04-12T22:56:17.049457+00:00"}, 
 {"id":"8edef0bc-33c6-4863-8d8c-dd0758eb5f7b","employee_id":"emp_1","employee_name":"Cat","customer_type":"standard","items":[{"name": "Pistol Ammo", "quantity": 4, "productId": "co_2", "unitPrice": 3, "commission": 4.199999999999999, "totalPrice": 12, "discountedPrice": 3}, {"name": "Pump-Action", "quantity": 1, "productId": "sg_5", "unitPrice": 75, "commission": 26.25, "totalPrice": 75, "discountedPrice": 75}],"total_amount":87.00,"total_commission":30.45,"ledger_amount":56.55,"timestamp":"2026-04-12T20:35:39.186Z","created_at":"2026-04-12T20:37:13.255587+00:00","updated_at":"2026-04-12T20:37:13.255587+00:00"}, 
 {"id":"a15381d3-a7b3-4c21-9a97-3b073b00c40d","employee_id":"emp_1","employee_name":"Cat","customer_type":"standard","items":[{"name": "Double Barrel", "quantity": 1, "productId": "sg_2", "unitPrice": 45, "commission": 15.749999999999998, "totalPrice": 45, "discountedPrice": 45}],"total_amount":45.00,"total_commission":15.75,"ledger_amount":29.25,"timestamp":"2026-04-12T20:25:45.868Z","created_at":"2026-04-12T20:27:19.447034+00:00","updated_at":"2026-04-12T20:27:19.447034+00:00"}, 
 {"id":"dc5f23b1-906a-4c3b-bbaf-7657992bfc95","employee_id":"emp_1","employee_name":"Cat","customer_type":"standard","items":[{"name": "Winchester", "quantity": 1, "productId": "rp_3", "unitPrice": 55, "commission": 19.25, "totalPrice": 55, "discountedPrice": 55}],"total_amount":55.00,"total_commission":19.25,"ledger_amount":35.75,"timestamp":"2026-04-12T20:01:50.074Z","created_at":"2026-04-12T20:03:24.237926+00:00","updated_at":"2026-04-12T20:03:24.237926+00:00"}, 
 {"id":"5f70ec2a-9fed-420a-a299-b9be0c908208","employee_id":"emp_1","employee_name":"Cat","customer_type":"standard","items":[{"name": "Colt 1911", "quantity": 1, "productId": "pi_1", "unitPrice": 450, "commission": 157.5, "totalPrice": 450, "discountedPrice": 450}],"total_amount":450.00,"total_commission":157.50,"ledger_amount":292.50,"timestamp":"2026-04-12T19:48:30.538Z","created_at":"2026-04-12T19:50:04.717989+00:00","updated_at":"2026-04-12T19:50:04.717989+00:00"}, 
 {"id":"1105b6d4-3513-4836-b9fe-68666dce15bf","employee_id":"emp_1","employee_name":"Cat","customer_type":"standard","items":[{"name": "LeMat", "quantity": 2, "productId": "rv_4", "unitPrice": 35, "commission": 24.5, "totalPrice": 70, "discountedPrice": 35}],"total_amount":70.00,"total_commission":24.50,"ledger_amount":45.50,"timestamp":"2026-04-12T19:09:50.568Z","created_at":"2026-04-12T19:11:24.525603+00:00","updated_at":"2026-04-12T19:11:24.525603+00:00"}, 
 {"id":"1f33f15f-143d-4836-9c10-ba465aa47504","employee_id":"emp_1","employee_name":"Cat","customer_type":"standard","items":[{"name": "Pump-Action", "quantity": 1, "productId": "sg_5", "unitPrice": 75, "commission": 26.25, "totalPrice": 75, "discountedPrice": 75}],"total_amount":75.00,"total_commission":26.25,"ledger_amount":48.75,"timestamp":"2026-04-12T18:54:58.348Z","created_at":"2026-04-12T18:56:31.67136+00:00","updated_at":"2026-04-12T18:56:31.67136+00:00"}, 
 {"id":"06b4f44d-257c-4222-803b-884a27e2084c","employee_id":"emp_mnuy6bg7_tuj0qu","employee_name":"Colt","customer_type":"standard","items":[{"name": "Navy", "quantity": 1, "productId": "rv_3", "unitPrice": 35, "commission": 12.25, "totalPrice": 35, "discountedPrice": 35}, {"name": "Sawn-Off", "quantity": 1, "productId": "sg_1", "unitPrice": 35, "commission": 12.25, "totalPrice": 35, "discountedPrice": 35}],"total_amount":70.00,"total_commission":24.50,"ledger_amount":45.50,"timestamp":"2026-04-12T17:34:56.404Z","created_at":"2026-04-12T17:34:57.246863+00:00","updated_at":"2026-04-12T17:34:57.246863+00:00"}, 
 {"id":"42fcd4ab-dbec-4116-9ad8-68079d0b358a","employee_id":"emp_1","employee_name":"Cat","customer_type":"standard","items":[{"name": "LeMat", "quantity": 1, "productId": "rv_4", "unitPrice": 35, "commission": 12.25, "totalPrice": 35, "discountedPrice": 35}],"total_amount":35.00,"total_commission":12.25,"ledger_amount":22.75,"timestamp":"2026-04-10T23:37:14.819Z","created_at":"2026-04-10T23:38:44.011574+00:00","updated_at":"2026-04-10T23:38:44.011574+00:00"}, 
 {"id":"e2f7eb02-beea-4973-8e1a-3842eb6acab1","employee_id":"emp_1","employee_name":"Cat","customer_type":"standard","items":[{"name": "Bolt-Action", "quantity": 1, "productId": "rf_3", "unitPrice": 75, "commission": 26.25, "totalPrice": 75, "discountedPrice": 75}, {"name": "Sawn-Off", "quantity": 2, "productId": "sg_1", "unitPrice": 35, "commission": 24.5, "totalPrice": 70, "discountedPrice": 35}],"total_amount":145.00,"total_commission":50.75,"ledger_amount":94.25,"timestamp":"2026-04-10T21:31:08.725Z","created_at":"2026-04-10T21:32:38.595056+00:00","updated_at":"2026-04-10T21:32:38.595056+00:00"}, 
 {"id":"0520d228-2e55-4e96-8db9-8b49dc3cf7be","employee_id":"emp_1","employee_name":"Cat","customer_type":"standard","items":[{"name": "Mauser", "quantity": 2, "productId": "pi_2", "unitPrice": 35, "commission": 24.5, "totalPrice": 70, "discountedPrice": 35}, {"name": "Pistol Ammo", "quantity": 2, "productId": "co_2", "unitPrice": 3, "commission": 2.0999999999999996, "totalPrice": 6, "discountedPrice": 3}],"total_amount":76.00,"total_commission":26.60,"ledger_amount":49.40,"timestamp":"2026-04-08T22:25:37.269Z","created_at":"2026-04-08T22:27:03.277596+00:00","updated_at":"2026-04-08T22:27:03.277596+00:00"}, 
 {"id":"a30b77a4-0335-4a82-a1c9-0a398855fbc7","employee_id":"emp_1","employee_name":"Cat","customer_type":"standard","items":[{"name": "Volcanic", "quantity": 1, "productId": "pi_4", "unitPrice": 35, "commission": 12.25, "totalPrice": 35, "discountedPrice": 35}],"total_amount":35.00,"total_commission":12.25,"ledger_amount":22.75,"timestamp":"2026-04-07T20:53:53.722Z","created_at":"2026-04-07T20:55:16.630056+00:00","updated_at":"2026-04-07T20:55:16.630056+00:00"}, 
 {"id":"bbd686ae-253f-4d66-80a2-455225584b68","employee_id":"emp_1","employee_name":"Cat","customer_type":"standard","items":[{"name": "1899", "quantity": 1, "productId": "pi_6", "unitPrice": 450, "commission": 157.5, "totalPrice": 450, "discountedPrice": 450}],"total_amount":450.00,"total_commission":157.50,"ledger_amount":292.50,"timestamp":"2026-04-06T21:40:51.004Z","created_at":"2026-04-06T21:42:12.230089+00:00","updated_at":"2026-04-06T21:42:12.230089+00:00"}, 
 {"id":"73c81168-fa01-41cc-92c2-e6e1a33cb8d3","employee_id":"emp_1","employee_name":"Cat","customer_type":"standard","items":[{"name": "Bolt-Action", "quantity": 1, "productId": "rf_3", "unitPrice": 75, "commission": 26.25, "totalPrice": 75, "discountedPrice": 75}, {"name": "Navy", "quantity": 1, "productId": "rv_3", "unitPrice": 35, "commission": 12.25, "totalPrice": 35, "discountedPrice": 35}],"total_amount":110.00,"total_commission":38.50,"ledger_amount":71.50,"timestamp":"2026-04-04T22:09:22.143Z","created_at":"2026-04-04T22:10:39.371874+00:00","updated_at":"2026-04-04T22:10:39.371874+00:00"}, 
 {"id":"65f4f7db-4ac6-4050-ad1c-743d3c23c71b","employee_id":"emp_1","employee_name":"Cat","customer_type":"standard","items":[{"name": "Mare's Leg", "quantity": 1, "productId": "rp_4", "unitPrice": 350, "commission": 122.49999999999999, "totalPrice": 350, "discountedPrice": 350}],"total_amount":350.00,"total_commission":122.50,"ledger_amount":227.50,"timestamp":"2026-04-04T21:56:05.786Z","created_at":"2026-04-04T21:57:22.642981+00:00","updated_at":"2026-04-04T21:57:22.642981+00:00"}, 
 {"id":"8e16adf0-1026-4f53-852c-22fd5b4c4740","employee_id":"emp_1","employee_name":"Cat","customer_type":"standard","items":[{"name": "Bolt-Action", "quantity": 1, "productId": "rf_3", "unitPrice": 75, "commission": 26.25, "totalPrice": 75, "discountedPrice": 75}],"total_amount":75.00,"total_commission":26.25,"ledger_amount":48.75,"timestamp":"2026-04-04T20:58:35.294Z","created_at":"2026-04-04T20:59:52.516946+00:00","updated_at":"2026-04-04T20:59:52.516946+00:00"}, 
 {"id":"8f1da5df-f61f-4ae1-b92b-91246cb96f84","employee_id":"emp_1","employee_name":"Cat","customer_type":"standard","items":[{"name": "Colt 1911", "quantity": 1, "productId": "pi_1", "unitPrice": 450, "commission": 157.5, "totalPrice": 450, "discountedPrice": 450}, {"name": "Pistol Ammo", "quantity": 6, "productId": "co_2", "unitPrice": 3, "commission": 6.3, "totalPrice": 18, "discountedPrice": 3}],"total_amount":468.00,"total_commission":163.80,"ledger_amount":304.20,"timestamp":"2026-04-04T01:37:59.627Z","created_at":"2026-04-04T01:39:14.925086+00:00","updated_at":"2026-04-04T01:39:14.925086+00:00"}, 
 {"id":"4c58f2fe-5d59-4dfd-9b06-2db219a4439e","employee_id":"emp_1","employee_name":"Cat","customer_type":"standard","items":[{"name": "Pump-Action", "quantity": 1, "productId": "sg_5", "unitPrice": 75, "commission": 26.25, "totalPrice": 75, "discountedPrice": 75}],"total_amount":75.00,"total_commission":26.25,"ledger_amount":48.75,"timestamp":"2026-04-03T03:15:19.261Z","created_at":"2026-04-03T03:16:32.865323+00:00","updated_at":"2026-04-03T03:16:32.865323+00:00"}, 
 {"id":"43666f21-ada9-4369-9679-75ebfa5087d4","employee_id":"emp_1","employee_name":"Cat","customer_type":"standard","items":[{"name": "Henry", "quantity": 1, "productId": "rp_5", "unitPrice": 370, "commission": 129.5, "totalPrice": 370, "discountedPrice": 370}],"total_amount":370.00,"total_commission":129.50,"ledger_amount":240.50,"timestamp":"2026-04-03T00:44:46.369Z","created_at":"2026-04-03T00:45:59.815564+00:00","updated_at":"2026-04-03T00:45:59.815564+00:00"}, 
 {"id":"f03c4f06-91ab-4ce7-9072-7679826f30aa","employee_id":"emp_1","employee_name":"Cat","customer_type":"standard","items":[{"name": "Mauser", "quantity": 2, "productId": "pi_2", "unitPrice": 35, "commission": 24.5, "totalPrice": 70, "discountedPrice": 35}, {"name": "Sharps / Martini", "quantity": 1, "productId": "rf_4", "unitPrice": 350, "commission": 122.49999999999999, "totalPrice": 350, "discountedPrice": 350}, {"name": "Pistol Ammo", "quantity": 5, "productId": "co_2", "unitPrice": 3, "commission": 5.25, "totalPrice": 15, "discountedPrice": 3}],"total_amount":435.00,"total_commission":152.25,"ledger_amount":282.75,"timestamp":"2026-04-02T23:49:13.820Z","created_at":"2026-04-02T23:50:27.017365+00:00","updated_at":"2026-04-02T23:50:27.017365+00:00"}, 
 {"id":"7f1db220-c5a7-4c4e-9691-5c1a15112f81","employee_id":"emp_1","employee_name":"Cat","customer_type":"standard","items":[{"name": "Colt 1911", "quantity": 1, "productId": "pi_1", "unitPrice": 450, "commission": 157.5, "totalPrice": 450, "discountedPrice": 450}, {"name": "Pistol Ammo", "quantity": 10, "productId": "co_2", "unitPrice": 3, "commission": 10.5, "totalPrice": 30, "discountedPrice": 3}],"total_amount":480.00,"total_commission":168.00,"ledger_amount":312.00,"timestamp":"2026-04-02T23:34:25.316Z","created_at":"2026-04-02T23:35:38.788998+00:00","updated_at":"2026-04-02T23:35:38.788998+00:00"}, 
 {"id":"3fbbce80-437b-4c7e-a6a0-2776653c25d5","employee_id":"emp_1","employee_name":"Cat","customer_type":"standard","items":[{"name": "Bolt-Action", "quantity": 1, "productId": "rf_3", "unitPrice": 75, "commission": 26.25, "totalPrice": 75, "discountedPrice": 75}],"total_amount":75.00,"total_commission":26.25,"ledger_amount":48.75,"timestamp":"2026-04-02T00:49:49.789Z","created_at":"2026-04-02T00:51:01.761718+00:00","updated_at":"2026-04-02T00:51:01.761718+00:00"}, 
 {"id":"f55474e3-689b-4e99-8661-4abf1f3c03b4","employee_id":"emp_1","employee_name":"Cat","customer_type":"standard","items":[{"name": "Henry", "quantity": 1, "productId": "rp_5", "unitPrice": 370, "commission": 129.5, "totalPrice": 370, "discountedPrice": 370}, {"name": "Engraving Plate", "quantity": 1, "productId": "co_5", "unitPrice": 20, "commission": 7, "totalPrice": 20, "discountedPrice": 20}],"total_amount":390.00,"total_commission":136.50,"ledger_amount":253.50,"timestamp":"2026-04-01T23:16:15.364Z","created_at":"2026-04-01T23:17:26.82923+00:00","updated_at":"2026-04-01T23:17:26.82923+00:00"}, 
 {"id":"04230f05-acb1-4bb3-aa37-83113f22fe10","employee_id":"emp_1","employee_name":"Cat","customer_type":"standard","items":[{"name": "Winchester", "quantity": 1, "productId": "rp_3", "unitPrice": 55, "commission": 19.25, "totalPrice": 55, "discountedPrice": 55}, {"name": "LeMat", "quantity": 2, "productId": "rv_4", "unitPrice": 35, "commission": 24.5, "totalPrice": 70, "discountedPrice": 35}],"total_amount":125.00,"total_commission":43.75,"ledger_amount":81.25,"timestamp":"2026-04-01T22:49:48.999Z","created_at":"2026-04-01T22:51:00.280118+00:00","updated_at":"2026-04-01T22:51:00.280118+00:00"}, 
 {"id":"d550cfa1-8690-43a8-a59c-115df2a4bf1e","employee_id":"emp_1","employee_name":"Cat","customer_type":"standard","items":[{"name": "Bolt-Action", "quantity": 1, "productId": "rf_3", "unitPrice": 75, "commission": 26.25, "totalPrice": 75, "discountedPrice": 75}],"total_amount":75.00,"total_commission":26.25,"ledger_amount":48.75,"timestamp":"2026-03-31T01:43:16.893Z","created_at":"2026-03-31T01:44:24.885445+00:00","updated_at":"2026-03-31T01:44:24.885445+00:00"}, 
 {"id":"020f6862-1b79-4a81-a9c6-a2639c5dfc0c","employee_id":"emp_1","employee_name":"Cat","customer_type":"standard","items":[{"name": "LeMat", "quantity": 2, "productId": "rv_4", "unitPrice": 35, "commission": 24.5, "totalPrice": 70, "discountedPrice": 35}, {"name": "Springfield", "quantity": 1, "productId": "rf_1", "unitPrice": 70, "commission": 24.5, "totalPrice": 70, "discountedPrice": 70}],"total_amount":140.00,"total_commission":49.00,"ledger_amount":91.00,"timestamp":"2026-03-30T21:39:21.371Z","created_at":"2026-03-30T21:40:28.201028+00:00","updated_at":"2026-03-30T21:40:28.201028+00:00"}, 
 {"id":"3b925ffa-909d-4258-ac23-3e30208d87b3","employee_id":"emp_1","employee_name":"Cat","customer_type":"standard","items":[{"name": "Navy", "quantity": 1, "productId": "rv_3", "unitPrice": 35, "commission": 12.25, "totalPrice": 35, "discountedPrice": 35}],"total_amount":35.00,"total_commission":12.25,"ledger_amount":22.75,"timestamp":"2026-03-30T20:00:08.192Z","created_at":"2026-03-30T20:01:15.210438+00:00","updated_at":"2026-03-30T20:01:15.210438+00:00"}, 
 {"id":"c6637256-0024-470b-bdc4-a74bd94925d5","employee_id":"emp_1","employee_name":"Cat","customer_type":"standard","items":[{"name": "Winchester", "quantity": 1, "productId": "rp_3", "unitPrice": 55, "commission": 19.25, "totalPrice": 55, "discountedPrice": 55}, {"name": "LeMat", "quantity": 2, "productId": "rv_4", "unitPrice": 35, "commission": 24.5, "totalPrice": 70, "discountedPrice": 35}],"total_amount":125.00,"total_commission":43.75,"ledger_amount":81.25,"timestamp":"2026-03-30T19:58:43.596Z","created_at":"2026-03-30T19:59:51.444411+00:00","updated_at":"2026-03-30T19:59:51.444411+00:00"}, 
 {"id":"8285c088-e4eb-4e2b-a26e-8ec65ee90168","employee_id":"emp_1","employee_name":"Cat","customer_type":"standard","items":[{"name": "Semi-Auto", "quantity": 1, "productId": "sg_3", "unitPrice": 55, "commission": 19.25, "totalPrice": 55, "discountedPrice": 55}, {"name": "Double Barrel", "quantity": 1, "productId": "sg_2", "unitPrice": 45, "commission": 15.749999999999998, "totalPrice": 45, "discountedPrice": 45}],"total_amount":100.00,"total_commission":35.00,"ledger_amount":65.00,"timestamp":"2026-03-29T22:32:29.644Z","created_at":"2026-03-29T22:33:34.932803+00:00","updated_at":"2026-03-29T22:33:34.932803+00:00"}, 
 {"id":"a3d925e2-9d81-401a-a1b9-5eda8a5be661","employee_id":"emp_1","employee_name":"Cat","customer_type":"standard","items":[{"name": "Semi-Auto", "quantity": 1, "productId": "sg_3", "unitPrice": 55, "commission": 19.25, "totalPrice": 55, "discountedPrice": 55}],"total_amount":55.00,"total_commission":19.25,"ledger_amount":35.75,"timestamp":"2026-03-29T22:09:39.053Z","created_at":"2026-03-29T22:10:44.41867+00:00","updated_at":"2026-03-29T22:10:44.41867+00:00"}, 
 {"id":"6847816b-666b-4ae7-87c9-84d0ba669f7b","employee_id":"emp_1","employee_name":"Cat","customer_type":"standard","items":[{"name": "Exotic Double", "quantity": 1, "productId": "sg_7", "unitPrice": 400, "commission": 140, "totalPrice": 400, "discountedPrice": 400}],"total_amount":400.00,"total_commission":140.00,"ledger_amount":260.00,"timestamp":"2026-03-29T21:52:30.417Z","created_at":"2026-03-29T21:53:35.644338+00:00","updated_at":"2026-03-29T21:53:35.644338+00:00"}, 
 {"id":"2d9cf3e0-fc85-4e44-8131-7f99e04fc1b7","employee_id":"emp_1","employee_name":"Cat","customer_type":"standard","items":[{"name": "Navy", "quantity": 1, "productId": "rv_3", "unitPrice": 35, "commission": 12.25, "totalPrice": 35, "discountedPrice": 35}],"total_amount":35.00,"total_commission":12.25,"ledger_amount":22.75,"timestamp":"2026-03-29T03:20:56.661Z","created_at":"2026-03-29T03:21:59.403684+00:00","updated_at":"2026-03-29T03:21:59.403684+00:00"}, 
 {"id":"16564b8c-29c3-48be-81f4-c64f98c12304","employee_id":"emp_1","employee_name":"Cat","customer_type":"standard","items":[{"name": "Pump-Action", "quantity": 1, "productId": "sg_5", "unitPrice": 75, "commission": 26.25, "totalPrice": 75, "discountedPrice": 75}],"total_amount":75.00,"total_commission":26.25,"ledger_amount":48.75,"timestamp":"2026-03-29T03:20:46.517Z","created_at":"2026-03-29T03:21:50.026437+00:00","updated_at":"2026-03-29T03:21:50.026437+00:00"}, 
 {"id":"2e3bad86-33c9-4cfe-af1a-559546a3814a","employee_id":"emp_1","employee_name":"Cat","customer_type":"standard","items":[{"name": "Navy", "quantity": 1, "productId": "rv_3", "unitPrice": 35, "commission": 12.25, "totalPrice": 35, "discountedPrice": 35}],"total_amount":35.00,"total_commission":12.25,"ledger_amount":22.75,"timestamp":"2026-03-28T22:46:20.315Z","created_at":"2026-03-28T22:47:23.551169+00:00","updated_at":"2026-03-28T22:47:23.551169+00:00"}, 
 {"id":"7defe7a8-784a-4e48-8996-b2c62e679e76","employee_id":"emp_1","employee_name":"Cat","customer_type":"standard","items":[{"name": "Colt 1911", "quantity": 1, "productId": "pi_1", "unitPrice": 450, "commission": 157.5, "totalPrice": 450, "discountedPrice": 450}],"total_amount":450.00,"total_commission":157.50,"ledger_amount":292.50,"timestamp":"2026-03-28T19:10:01.004Z","created_at":"2026-03-28T19:11:03.991749+00:00","updated_at":"2026-03-28T19:11:03.991749+00:00"}, 
 {"id":"8ef47930-b7ba-46bd-a352-a5a50ae91627","employee_id":"emp_1","employee_name":"Cat","customer_type":"standard","items":[{"name": "Henry", "quantity": 1, "productId": "rp_5", "unitPrice": 370, "commission": 129.5, "totalPrice": 370, "discountedPrice": 370}, {"name": "Engraving Plate", "quantity": 1, "productId": "co_5", "unitPrice": 20, "commission": 7, "totalPrice": 20, "discountedPrice": 20}],"total_amount":390.00,"total_commission":136.50,"ledger_amount":253.50,"timestamp":"2026-03-28T00:58:53.262Z","created_at":"2026-03-28T00:59:54.338212+00:00","updated_at":"2026-03-28T00:59:54.338212+00:00"}, 
 {"id":"3193c875-4ffb-4109-8808-c48c12b352e4","employee_id":"emp_1","employee_name":"Cat","customer_type":"standard","items":[{"name": "Pistol Ammo", "quantity": 2, "productId": "co_2", "unitPrice": 3, "commission": 2.0999999999999996, "totalPrice": 6, "discountedPrice": 3}],"total_amount":6.00,"total_commission":2.10,"ledger_amount":3.90,"timestamp":"2026-03-27T02:08:10.678Z","created_at":"2026-03-27T02:09:10.253855+00:00","updated_at":"2026-03-27T02:09:10.253855+00:00"}, 
 {"id":"d63cd87b-0c42-4b96-8f45-a4c4be755d8b","employee_id":"emp_1","employee_name":"Cat","customer_type":"standard","items":[{"name": "Semi-Auto", "quantity": 1, "productId": "sg_3", "unitPrice": 55, "commission": 19.25, "totalPrice": 55, "discountedPrice": 55}, {"name": "Coach Gun", "quantity": 1, "productId": "sg_6", "unitPrice": 300, "commission": 105, "totalPrice": 300, "discountedPrice": 300}],"total_amount":355.00,"total_commission":124.25,"ledger_amount":230.75,"timestamp":"2026-03-27T01:50:56.634Z","created_at":"2026-03-27T01:51:56.183443+00:00","updated_at":"2026-03-27T01:51:56.183443+00:00"}, 
 {"id":"c91e4583-d704-4ec1-a6f2-cfb06bd20685","employee_id":"emp_1","employee_name":"Cat","customer_type":"standard","items":[{"name": "Pump-Action", "quantity": 1, "productId": "sg_5", "unitPrice": 75, "commission": 26.25, "totalPrice": 75, "discountedPrice": 75}],"total_amount":75.00,"total_commission":26.25,"ledger_amount":48.75,"timestamp":"2026-03-25T23:15:53.581Z","created_at":"2026-03-25T23:16:51.378299+00:00","updated_at":"2026-03-25T23:16:51.378299+00:00"}, 
 {"id":"9119cdee-2ca3-469e-8c73-ee6ce4458f9a","employee_id":"emp_1","employee_name":"Cat","customer_type":"standard","items":[{"name": "Colt 1911", "quantity": 1, "productId": "pi_1", "unitPrice": 450, "commission": 157.5, "totalPrice": 450, "discountedPrice": 450}],"total_amount":450.00,"total_commission":157.50,"ledger_amount":292.50,"timestamp":"2026-03-23T20:13:30.755Z","created_at":"2026-03-23T20:14:24.667026+00:00","updated_at":"2026-03-23T20:14:24.667026+00:00"}, 
 {"id":"4cb9e48e-5e97-4a70-b327-97b1ac10a5a6","employee_id":"emp_1","employee_name":"Cat","customer_type":"standard","items":[{"name": "Gun Oil", "quantity": 10, "productId": "co_1", "unitPrice": 0.5, "commission": 1.75, "totalPrice": 5, "discountedPrice": 0.5}, {"name": "Pistol Ammo", "quantity": 4, "productId": "co_2", "unitPrice": 3, "commission": 4.199999999999999, "totalPrice": 12, "discountedPrice": 3}],"total_amount":17.00,"total_commission":5.95,"ledger_amount":11.05,"timestamp":"2026-03-23T01:07:51.453Z","created_at":"2026-03-23T01:08:44.263304+00:00","updated_at":"2026-03-23T01:08:44.263304+00:00"}, 
 {"id":"56c6aaba-f4eb-4ed8-92b3-9f754a3cefc9","employee_id":"emp_1","employee_name":"Cat","customer_type":"standard","items":[{"name": "Engraving Plate", "quantity": 1, "productId": "co_5", "unitPrice": 20, "commission": 7, "totalPrice": 20, "discountedPrice": 20}],"total_amount":20.00,"total_commission":7.00,"ledger_amount":13.00,"timestamp":"2026-03-22T01:05:08.644Z","created_at":"2026-03-22T01:05:58.263457+00:00","updated_at":"2026-03-22T01:05:58.263457+00:00"}, 
 {"id":"ffa39a57-c87e-4d5b-8b7a-5a923e033fd7","employee_id":"emp_1","employee_name":"Cat","customer_type":"standard","items":[{"name": "Mosin", "quantity": 1, "productId": "rf_7", "unitPrice": 400, "commission": 140, "totalPrice": 400, "discountedPrice": 400}],"total_amount":400.00,"total_commission":140.00,"ledger_amount":260.00,"timestamp":"2026-03-21T03:23:35.603Z","created_at":"2026-03-21T03:24:23.706805+00:00","updated_at":"2026-03-21T03:24:23.706805+00:00"}, 
 {"id":"7aa14b89-84ad-438e-8bcb-af23ae9b483f","employee_id":"emp_1","employee_name":"Cat","customer_type":"standard","items":[{"name": "Pistol Ammo", "quantity": 3, "productId": "co_2", "unitPrice": 3, "commission": 3.15, "totalPrice": 9, "discountedPrice": 3}],"total_amount":9.00,"total_commission":3.15,"ledger_amount":5.85,"timestamp":"2026-03-21T02:33:47.733Z","created_at":"2026-03-21T02:34:36.491982+00:00","updated_at":"2026-03-21T02:34:36.491982+00:00"}, 
 {"id":"acedd534-4ba0-4983-a7e2-08124fa1543c","employee_id":"emp_1","employee_name":"Cat","customer_type":"standard","items":[{"name": "Bolt-Action", "quantity": 1, "productId": "rf_3", "unitPrice": 75, "commission": 26.25, "totalPrice": 75, "discountedPrice": 75}],"total_amount":75.00,"total_commission":26.25,"ledger_amount":48.75,"timestamp":"2026-03-21T02:09:38.677Z","created_at":"2026-03-21T02:10:26.834789+00:00","updated_at":"2026-03-21T02:10:26.834789+00:00"}, 
 {"id":"391f7d96-37f1-4d8c-821d-9202d3950fce","employee_id":"emp_1","employee_name":"Cat","customer_type":"standard","items":[{"name": "Carcano", "quantity": 1, "productId": "rf_10", "unitPrice": 1000, "commission": 350, "totalPrice": 1000, "discountedPrice": 1000}],"total_amount":1000.00,"total_commission":350.00,"ledger_amount":650.00,"timestamp":"2026-03-21T00:42:17.298Z","created_at":"2026-03-21T00:43:05.610149+00:00","updated_at":"2026-03-21T00:43:05.610149+00:00"}, 
 {"id":"3952074e-cf1c-43d2-a193-c3747c207e17","employee_id":"emp_1","employee_name":"Cat","customer_type":"standard","items":[{"name": "Schofield", "quantity": 1, "productId": "rv_1", "unitPrice": 10, "commission": 3.5, "totalPrice": 10, "discountedPrice": 10}],"total_amount":10.00,"total_commission":3.50,"ledger_amount":6.50,"timestamp":"2026-03-18T20:30:57.985Z","created_at":"2026-03-18T20:31:43.296555+00:00","updated_at":"2026-03-18T20:31:43.296555+00:00"}, 
 {"id":"24c5f925-f5ab-428f-a386-052f5cb1eb42","employee_id":"emp_1","employee_name":"Cat","customer_type":"standard","items":[{"name": "Navy", "quantity": 1, "productId": "rv_3", "unitPrice": 35, "commission": 12.25, "totalPrice": 35, "discountedPrice": 35}],"total_amount":35.00,"total_commission":12.25,"ledger_amount":22.75,"timestamp":"2026-03-18T20:17:39.624Z","created_at":"2026-03-18T20:18:24.727426+00:00","updated_at":"2026-03-18T20:18:24.727426+00:00"}, 
 {"id":"a3628e2e-62ab-41f1-a755-e3d6523c1ac1","employee_id":"emp_1","employee_name":"Cat","customer_type":"standard","items":[{"name": "LeMat", "quantity": 2, "productId": "rv_4", "unitPrice": 35, "commission": 24.5, "totalPrice": 70, "discountedPrice": 35}],"total_amount":70.00,"total_commission":24.50,"ledger_amount":45.50,"timestamp":"2026-03-18T19:34:58.397Z","created_at":"2026-03-18T19:35:43.841934+00:00","updated_at":"2026-03-18T19:35:43.841934+00:00"}, 
 {"id":"bb021f0b-d511-4de5-9805-ab446c0e041c","employee_id":"emp_mlx7pd1m_caf25n","employee_name":"Mateo","customer_type":"standard","items":[{"name": "Bolt-Action", "quantity": 1, "productId": "rf_3", "unitPrice": 75, "commission": 26.25, "totalPrice": 75, "discountedPrice": 75}],"total_amount":75.00,"total_commission":26.25,"ledger_amount":48.75,"timestamp":"2026-03-16T21:32:40.643Z","created_at":"2026-03-16T21:33:21.164317+00:00","updated_at":"2026-03-16T21:33:21.164317+00:00"}, 
 {"id":"d265afd3-52a3-4d2a-90a2-89146565dec9","employee_id":"emp_mlx7pd1m_caf25n","employee_name":"Mateo","customer_type":"standard","items":[{"name": "Springfield", "quantity": 1, "productId": "rf_1", "unitPrice": 70, "commission": 24.5, "totalPrice": 70, "discountedPrice": 70}],"total_amount":70.00,"total_commission":24.50,"ledger_amount":45.50,"timestamp":"2026-03-16T20:45:03.131Z","created_at":"2026-03-16T20:45:43.16934+00:00","updated_at":"2026-03-16T20:45:43.16934+00:00"}, 
 {"id":"6d39a1a7-b8be-41e1-9bf9-91d4d32cf3ce","employee_id":"emp_1","employee_name":"Cat","customer_type":"standard","items":[{"name": "Engraving Plate", "quantity": 1, "productId": "co_5", "unitPrice": 20, "commission": 7, "totalPrice": 20, "discountedPrice": 20}],"total_amount":20.00,"total_commission":7.00,"ledger_amount":13.00,"timestamp":"2026-03-14T00:17:10.928Z","created_at":"2026-03-14T00:17:45.942606+00:00","updated_at":"2026-03-14T00:17:45.942606+00:00"}, 
 {"id":"63f2f407-19a9-49a9-a6c7-9ce456e63d3b","employee_id":"emp_1","employee_name":"Cat","customer_type":"standard","items":[{"name": "Winchester", "quantity": 1, "productId": "rp_3", "unitPrice": 55, "commission": 19.25, "totalPrice": 55, "discountedPrice": 55}, {"name": "Springfield", "quantity": 1, "productId": "rf_1", "unitPrice": 70, "commission": 24.5, "totalPrice": 70, "discountedPrice": 70}],"total_amount":125.00,"total_commission":43.75,"ledger_amount":81.25,"timestamp":"2026-03-13T21:05:13.407Z","created_at":"2026-03-13T21:05:47.775403+00:00","updated_at":"2026-03-13T21:05:47.775403+00:00"}, 
 {"id":"78525e5f-5d91-4928-aa81-7925aa4b5eae","employee_id":"emp_1","employee_name":"Cat","customer_type":"standard","items":[{"name": "Bolt-Action", "quantity": 1, "productId": "rf_3", "unitPrice": 75, "commission": 26.25, "totalPrice": 75, "discountedPrice": 75}, {"name": "Winchester", "quantity": 1, "productId": "rp_3", "unitPrice": 55, "commission": 19.25, "totalPrice": 55, "discountedPrice": 55}],"total_amount":130.00,"total_commission":45.50,"ledger_amount":84.50,"timestamp":"2026-03-13T21:00:37.294Z","created_at":"2026-03-13T21:01:11.679774+00:00","updated_at":"2026-03-13T21:01:11.679774+00:00"}, 
 {"id":"41fa057a-6553-4fa5-9dd1-130a53587d45","employee_id":"emp_1","employee_name":"Cat","customer_type":"standard","items":[{"name": "Engraving Plate", "quantity": 1, "productId": "co_5", "unitPrice": 20, "commission": 7, "totalPrice": 20, "discountedPrice": 20}],"total_amount":20.00,"total_commission":7.00,"ledger_amount":13.00,"timestamp":"2026-03-13T20:53:15.077Z","created_at":"2026-03-13T20:53:49.581549+00:00","updated_at":"2026-03-13T20:53:49.581549+00:00"}, 
 {"id":"a917d743-6499-4b34-9866-eaf21bb51398","employee_id":"emp_1","employee_name":"Cat","customer_type":"standard","items":[{"name": "Pistol Ammo", "quantity": 6, "productId": "co_2", "unitPrice": 3, "commission": 6.3, "totalPrice": 18, "discountedPrice": 3}],"total_amount":18.00,"total_commission":6.30,"ledger_amount":11.70,"timestamp":"2026-03-13T20:17:44.709Z","created_at":"2026-03-13T20:18:18.871795+00:00","updated_at":"2026-03-13T20:18:18.871795+00:00"}, 
 {"id":"9b754027-c143-4f2a-a803-e8313fe46c55","employee_id":"emp_3","employee_name":"Rob","customer_type":"standard","items":[{"name": "Semi-Auto", "quantity": 10, "productId": "sg_3", "unitPrice": 55, "commission": 192.5, "totalPrice": 550, "discountedPrice": 55}],"total_amount":550.00,"total_commission":192.50,"ledger_amount":357.50,"timestamp":"2026-03-12T23:23:39.679Z","created_at":"2026-03-12T23:23:42.579565+00:00","updated_at":"2026-03-12T23:23:42.579565+00:00"}, 
 {"id":"4444ab3c-5a8c-4f99-9307-d113787370d3","employee_id":"emp_mlx7pd1m_caf25n","employee_name":"Mateo","customer_type":"standard","items":[{"name": "Pistol Ammo", "quantity": 2, "productId": "co_2", "unitPrice": 3, "commission": 2.0999999999999996, "totalPrice": 6, "discountedPrice": 3}],"total_amount":6.00,"total_commission":2.10,"ledger_amount":3.90,"timestamp":"2026-03-11T23:41:51.191Z","created_at":"2026-03-11T23:41:51.975945+00:00","updated_at":"2026-03-11T23:41:51.975945+00:00"}, 
 {"id":"df05dceb-d41e-4f86-9b81-797c5c6338ee","employee_id":"emp_mlx7pd1m_caf25n","employee_name":"Mateo","customer_type":"standard","items":[{"name": "Mosin", "quantity": 1, "productId": "rf_7", "unitPrice": 400, "commission": 140, "totalPrice": 400, "discountedPrice": 400}],"total_amount":400.00,"total_commission":140.00,"ledger_amount":260.00,"timestamp":"2026-03-11T23:34:15.178Z","created_at":"2026-03-11T23:34:15.9721+00:00","updated_at":"2026-03-11T23:34:15.9721+00:00"}, 
 {"id":"88e7fb94-a440-4e9f-a73c-7991108b7d9f","employee_id":"emp_1","employee_name":"Cat","customer_type":"standard","items":[{"name": "Schofield", "quantity": 1, "productId": "rv_1", "unitPrice": 10, "commission": 3.5, "totalPrice": 10, "discountedPrice": 10}],"total_amount":10.00,"total_commission":3.50,"ledger_amount":6.50,"timestamp":"2026-03-11T23:29:48.387Z","created_at":"2026-03-11T23:30:19.287507+00:00","updated_at":"2026-03-11T23:30:19.287507+00:00"}, 
 {"id":"66f9e547-6dba-41ac-9e98-f41769bf04da","employee_id":"emp_1","employee_name":"Cat","customer_type":"standard","items":[{"name": "Rolling Block", "quantity": 1, "productId": "rf_9", "unitPrice": 1000, "commission": 350, "totalPrice": 1000, "discountedPrice": 1000}],"total_amount":1000.00,"total_commission":350.00,"ledger_amount":650.00,"timestamp":"2026-03-11T23:08:48.177Z","created_at":"2026-03-11T23:09:18.806332+00:00","updated_at":"2026-03-11T23:09:18.806332+00:00"}, 
 {"id":"5826b55a-b8ed-4e29-af9e-841655f3748f","employee_id":"emp_mlx7pd1m_caf25n","employee_name":"Mateo","customer_type":"law_doc","items":[{"name": "LeMat", "quantity": 2, "productId": "rv_4", "unitPrice": 35, "commission": 22.049999999999997, "totalPrice": 63, "discountedPrice": 31.5}],"total_amount":63.00,"total_commission":22.05,"ledger_amount":40.95,"timestamp":"2026-03-11T23:02:44.693Z","created_at":"2026-03-11T23:02:46.095925+00:00","updated_at":"2026-03-11T23:02:46.095925+00:00"}, 
 {"id":"173dd53f-8982-4c35-a561-036516ad14e8","employee_id":"emp_mlx7pd1m_caf25n","employee_name":"Mateo","customer_type":"standard","items":[{"name": "Schofield", "quantity": 1, "productId": "rv_1", "unitPrice": 10, "commission": 3.5, "totalPrice": 10, "discountedPrice": 10}],"total_amount":10.00,"total_commission":3.50,"ledger_amount":6.50,"timestamp":"2026-03-11T22:48:10.303Z","created_at":"2026-03-11T22:48:10.567634+00:00","updated_at":"2026-03-11T22:48:10.567634+00:00"}, 
 {"id":"04393f91-60f3-4c0f-a087-247f8a6f89a4","employee_id":"emp_1","employee_name":"Cat","customer_type":"standard","items":[{"name": "Gewehr 98", "quantity": 1, "productId": "rf_5", "unitPrice": 400, "commission": 140, "totalPrice": 400, "discountedPrice": 400}, {"name": "Navy", "quantity": 1, "productId": "rv_3", "unitPrice": 35, "commission": 12.25, "totalPrice": 35, "discountedPrice": 35}],"total_amount":435.00,"total_commission":152.25,"ledger_amount":282.75,"timestamp":"2026-03-11T21:14:32.620Z","created_at":"2026-03-11T21:15:03.532234+00:00","updated_at":"2026-03-11T21:15:03.532234+00:00"}, 
 {"id":"a750d7da-913e-439a-be13-133d45b0fb75","employee_id":"emp_1","employee_name":"Cat","customer_type":"standard","items":[{"name": "Weapon Crate", "quantity": 2, "productId": "co_mmgtowgz_i4z7", "unitPrice": 100, "commission": 70, "totalPrice": 200, "discountedPrice": 100}],"total_amount":200.00,"total_commission":70.00,"ledger_amount":130.00,"timestamp":"2026-03-11T20:53:55.163Z","created_at":"2026-03-11T20:54:25.449211+00:00","updated_at":"2026-03-11T20:54:25.449211+00:00"}, 
 {"id":"3d8d9e73-04f6-4af2-9450-2d1fa806aeeb","employee_id":"emp_1","employee_name":"Cat","customer_type":"standard","items":[{"name": "Sawn-Off", "quantity": 2, "productId": "sg_1", "unitPrice": 35, "commission": 24.5, "totalPrice": 70, "discountedPrice": 35}],"total_amount":70.00,"total_commission":24.50,"ledger_amount":45.50,"timestamp":"2026-03-10T21:43:21.794Z","created_at":"2026-03-10T21:43:50.707658+00:00","updated_at":"2026-03-10T21:43:50.707658+00:00"}, 
 {"id":"1bd4bb87-ca5c-47d4-9ddd-b22bb0063ae2","employee_id":"emp_1","employee_name":"Cat","customer_type":"standard","items":[{"name": "Weapon Crate", "quantity": 1, "productId": "co_mmgtowgz_i4z7", "unitPrice": 100, "commission": 35, "totalPrice": 100, "discountedPrice": 100}],"total_amount":100.00,"total_commission":35.00,"ledger_amount":65.00,"timestamp":"2026-03-10T20:57:08.214Z","created_at":"2026-03-10T20:57:37.119827+00:00","updated_at":"2026-03-10T20:57:37.119827+00:00"}, 
 {"id":"4446ac72-8b41-417b-b51e-c46a91ab8587","employee_id":"emp_1","employee_name":"Cat","customer_type":"standard","items":[{"name": "Weapon Crate", "quantity": 2, "productId": "co_mmgtowgz_i4z7", "unitPrice": 100, "commission": 70, "totalPrice": 200, "discountedPrice": 100}],"total_amount":200.00,"total_commission":70.00,"ledger_amount":130.00,"timestamp":"2026-03-10T19:58:48.835Z","created_at":"2026-03-10T19:59:16.752804+00:00","updated_at":"2026-03-10T19:59:16.752804+00:00"}, 
 {"id":"9da7befc-370d-4bf5-8dfb-b513d1cd0916","employee_id":"emp_1","employee_name":"Cat","customer_type":"standard","items":[{"name": "Engraving Plate", "quantity": 1, "productId": "co_5", "unitPrice": 20, "commission": 7, "totalPrice": 20, "discountedPrice": 20}],"total_amount":20.00,"total_commission":7.00,"ledger_amount":13.00,"timestamp":"2026-03-10T19:54:11.332Z","created_at":"2026-03-10T19:54:39.514258+00:00","updated_at":"2026-03-10T19:54:39.514258+00:00"}, 
 {"id":"568ca80a-53b4-476d-a0e6-4255ad83d62c","employee_id":"emp_1","employee_name":"Cat","customer_type":"standard","items":[{"name": "Double Action", "quantity": 2, "productId": "rv_2", "unitPrice": 25, "commission": 17.5, "totalPrice": 50, "discountedPrice": 25}],"total_amount":50.00,"total_commission":17.50,"ledger_amount":32.50,"timestamp":"2026-03-10T19:53:25.159Z","created_at":"2026-03-10T19:53:54.10155+00:00","updated_at":"2026-03-10T19:53:54.10155+00:00"}, 
 {"id":"18978ab5-d670-4e8d-9b73-4cc0c66a7d2c","employee_id":"emp_3","employee_name":"Rob","customer_type":"standard","items":[{"name": "Exotic Double", "quantity": 1, "productId": "sg_7", "unitPrice": 400, "commission": 140, "totalPrice": 400, "discountedPrice": 400}],"total_amount":400.00,"total_commission":140.00,"ledger_amount":260.00,"timestamp":"2026-03-08T23:32:46.601Z","created_at":"2026-03-08T23:32:47.958443+00:00","updated_at":"2026-03-08T23:32:47.958443+00:00"}, 
 {"id":"6866e1da-26ae-43a0-b5b7-cb7544864315","employee_id":"emp_1","employee_name":"Cat","customer_type":"standard","items":[{"name": "Winchester", "quantity": 1, "productId": "rp_3", "unitPrice": 55, "commission": 19.25, "totalPrice": 55, "discountedPrice": 55}, {"name": "Navy", "quantity": 2, "productId": "rv_3", "unitPrice": 35, "commission": 24.5, "totalPrice": 70, "discountedPrice": 35}],"total_amount":125.00,"total_commission":43.75,"ledger_amount":81.25,"timestamp":"2026-03-08T21:42:01.222Z","created_at":"2026-03-08T21:42:26.302004+00:00","updated_at":"2026-03-08T21:42:26.302004+00:00"}, 
 {"id":"7320eeb9-9ecb-416f-9a44-8f299c7768c7","employee_id":"emp_4","employee_name":"Morris","customer_type":"standard","items":[{"name": "Semi-Auto", "quantity": 1, "productId": "sg_3", "unitPrice": 55, "commission": 19.25, "totalPrice": 55, "discountedPrice": 55}],"total_amount":55.00,"total_commission":19.25,"ledger_amount":35.75,"timestamp":"2026-03-07T23:13:13.590Z","created_at":"2026-03-07T23:13:13.421105+00:00","updated_at":"2026-03-07T23:13:13.421105+00:00"}, 
 {"id":"caf72801-0087-4c64-a6b2-8e94fb37c935","employee_id":"emp_4","employee_name":"Morris","customer_type":"standard","items":[{"name": "1899", "quantity": 1, "productId": "pi_6", "unitPrice": 450, "commission": 157.5, "totalPrice": 450, "discountedPrice": 450}],"total_amount":450.00,"total_commission":157.50,"ledger_amount":292.50,"timestamp":"2026-03-07T22:35:38.789Z","created_at":"2026-03-07T22:35:39.240396+00:00","updated_at":"2026-03-07T22:35:39.240396+00:00"}, 
 {"id":"786880f2-802c-4519-bcdf-036a1e5b6941","employee_id":"emp_4","employee_name":"Morris","customer_type":"standard","items":[{"name": "Winchester", "quantity": 1, "productId": "rp_3", "unitPrice": 55, "commission": 19.25, "totalPrice": 55, "discountedPrice": 55}, {"name": "Gun Oil", "quantity": 5, "productId": "co_1", "unitPrice": 0.5, "commission": 0.875, "totalPrice": 2.5, "discountedPrice": 0.5}],"total_amount":57.50,"total_commission":20.13,"ledger_amount":37.38,"timestamp":"2026-03-07T22:28:43.592Z","created_at":"2026-03-07T22:28:43.928817+00:00","updated_at":"2026-03-07T22:28:43.928817+00:00"}, 
 {"id":"fd146ccb-a938-4c59-814c-f056dccafbdc","employee_id":"emp_4","employee_name":"Morris","customer_type":"standard","items":[{"name": "Bolt-Action", "quantity": 1, "productId": "rf_3", "unitPrice": 75, "commission": 26.25, "totalPrice": 75, "discountedPrice": 75}],"total_amount":75.00,"total_commission":26.25,"ledger_amount":48.75,"timestamp":"2026-03-07T21:26:31.086Z","created_at":"2026-03-07T21:26:31.432211+00:00","updated_at":"2026-03-07T21:26:31.432211+00:00"}, 
 {"id":"ed45dc57-dd84-4ad1-911c-6d7ee753c9ce","employee_id":"emp_4","employee_name":"Morris","customer_type":"standard","items":[{"name": "Gun Oil", "quantity": 13, "productId": "co_1", "unitPrice": 0.5, "commission": 2.275, "totalPrice": 6.5, "discountedPrice": 0.5}],"total_amount":6.50,"total_commission":2.28,"ledger_amount":4.23,"timestamp":"2026-03-07T20:59:02.757Z","created_at":"2026-03-07T20:59:03.191256+00:00","updated_at":"2026-03-07T20:59:03.191256+00:00"}, 
 {"id":"4ad1d911-129f-419b-9e31-88c7f2cb09fe","employee_id":"emp_4","employee_name":"Morris","customer_type":"standard","items":[{"name": "LeMat", "quantity": 2, "productId": "rv_4", "unitPrice": 35, "commission": 24.5, "totalPrice": 70, "discountedPrice": 35}, {"name": "Sawn-Off", "quantity": 1, "productId": "sg_1", "unitPrice": 35, "commission": 12.25, "totalPrice": 35, "discountedPrice": 35}, {"name": "Bolt-Action", "quantity": 1, "productId": "rf_3", "unitPrice": 75, "commission": 26.25, "totalPrice": 75, "discountedPrice": 75}],"total_amount":180.00,"total_commission":63.00,"ledger_amount":117.00,"timestamp":"2026-03-07T20:54:49.989Z","created_at":"2026-03-07T20:54:50.592074+00:00","updated_at":"2026-03-07T20:54:50.592074+00:00"}, 
 {"id":"2434777b-0b86-4048-81f5-6c3e7cba779e","employee_id":"emp_4","employee_name":"Morris","customer_type":"standard","items":[{"name": "Bolt-Action", "quantity": 1, "productId": "rf_3", "unitPrice": 75, "commission": 26.25, "totalPrice": 75, "discountedPrice": 75}],"total_amount":75.00,"total_commission":26.25,"ledger_amount":48.75,"timestamp":"2026-03-07T20:50:05.184Z","created_at":"2026-03-07T20:50:05.719866+00:00","updated_at":"2026-03-07T20:50:05.719866+00:00"}, 
 {"id":"006e37e4-5aea-409b-b577-b2dbbdd5eb13","employee_id":"emp_mlx7pd1m_caf25n","employee_name":"Mateo","customer_type":"standard","items":[{"name": "Navy", "quantity": 2, "productId": "rv_3", "unitPrice": 35, "commission": 24.5, "totalPrice": 70, "discountedPrice": 35}],"total_amount":70.00,"total_commission":24.50,"ledger_amount":45.50,"timestamp":"2026-03-06T03:58:43.830Z","created_at":"2026-03-06T03:58:45.410014+00:00","updated_at":"2026-03-06T03:58:45.410014+00:00"}, 
 {"id":"a5fa2902-0016-4634-87e6-b616c0c2514b","employee_id":"emp_1","employee_name":"Cat","customer_type":"standard","items":[{"name": "Henry", "quantity": 1, "productId": "rp_5", "unitPrice": 370, "commission": 129.5, "totalPrice": 370, "discountedPrice": 370}],"total_amount":370.00,"total_commission":129.50,"ledger_amount":240.50,"timestamp":"2026-03-06T03:26:08.606Z","created_at":"2026-03-06T03:26:27.387304+00:00","updated_at":"2026-03-06T03:26:27.387304+00:00"}, 
 {"id":"789d282f-fa48-46b5-8424-35aa19948d8e","employee_id":"emp_1","employee_name":"Cat","customer_type":"standard","items":[{"name": "Henry", "quantity": 1, "productId": "rp_5", "unitPrice": 370, "commission": 129.5, "totalPrice": 370, "discountedPrice": 370}],"total_amount":370.00,"total_commission":129.50,"ledger_amount":240.50,"timestamp":"2026-03-05T20:25:22.008Z","created_at":"2026-03-05T20:25:41.49833+00:00","updated_at":"2026-03-05T20:25:41.49833+00:00"}, 
 {"id":"ae5aa5d2-44f6-4172-9b70-917c7390bc45","employee_id":"emp_1","employee_name":"Cat","customer_type":"standard","items":[{"name": "Gun Oil", "quantity": 9, "productId": "co_1", "unitPrice": 0.5, "commission": 1.575, "totalPrice": 4.5, "discountedPrice": 0.5}],"total_amount":4.50,"total_commission":1.58,"ledger_amount":2.93,"timestamp":"2026-03-05T19:59:50.721Z","created_at":"2026-03-05T20:00:09.646127+00:00","updated_at":"2026-03-05T20:00:09.646127+00:00"}, 
 {"id":"4da745a4-b545-4e1f-9be4-f26ec367bdb9","employee_id":"emp_4","employee_name":"Morris","customer_type":"standard","items":[{"name": "Gun Oil", "quantity": 50, "productId": "co_1", "unitPrice": 0.5, "commission": 8.75, "totalPrice": 25, "discountedPrice": 0.5}],"total_amount":25.00,"total_commission":8.75,"ledger_amount":16.25,"timestamp":"2026-03-05T00:43:03.744Z","created_at":"2026-03-05T00:43:02.329047+00:00","updated_at":"2026-03-05T00:43:02.329047+00:00"}, 
 {"id":"a55e3d7e-b8a3-4b1b-81e2-c2471143445f","employee_id":"emp_4","employee_name":"Morris","customer_type":"standard","items":[{"name": "Winchester", "quantity": 1, "productId": "rp_3", "unitPrice": 55, "commission": 19.25, "totalPrice": 55, "discountedPrice": 55}, {"name": "Sawn-Off", "quantity": 1, "productId": "sg_1", "unitPrice": 35, "commission": 12.25, "totalPrice": 35, "discountedPrice": 35}, {"name": "LeMat", "quantity": 1, "productId": "rv_4", "unitPrice": 35, "commission": 12.25, "totalPrice": 35, "discountedPrice": 35}],"total_amount":125.00,"total_commission":43.75,"ledger_amount":81.25,"timestamp":"2026-03-05T00:42:54.017Z","created_at":"2026-03-05T00:42:52.609917+00:00","updated_at":"2026-03-05T00:42:52.609917+00:00"}, 
 {"id":"cf3b60f4-3a90-45f2-8be9-9e6a21316973","employee_id":"emp_1","employee_name":"Cat","customer_type":"standard","items":[{"name": "Colt 1911", "quantity": 1, "productId": "pi_1", "unitPrice": 450, "commission": 157.5, "totalPrice": 450, "discountedPrice": 450}],"total_amount":450.00,"total_commission":157.50,"ledger_amount":292.50,"timestamp":"2026-03-04T22:10:37.913Z","created_at":"2026-03-04T22:10:54.273616+00:00","updated_at":"2026-03-04T22:10:54.273616+00:00"}, 
 {"id":"220b5c8f-7006-4760-bcbd-0a039f74c949","employee_id":"emp_mlx7pd1m_caf25n","employee_name":"Mateo","customer_type":"standard","items":[{"name": "LeMat", "quantity": 2, "productId": "rv_4", "unitPrice": 35, "commission": 24.5, "totalPrice": 70, "discountedPrice": 35}],"total_amount":70.00,"total_commission":24.50,"ledger_amount":45.50,"timestamp":"2026-03-04T21:10:11.012Z","created_at":"2026-03-04T21:10:11.742328+00:00","updated_at":"2026-03-04T21:10:11.742328+00:00"}, 
 {"id":"f70fc844-abd0-4095-b6df-2b4d72d55a8d","employee_id":"emp_mlx7pd1m_caf25n","employee_name":"Mateo","customer_type":"standard","items":[{"name": "LeMat", "quantity": 2, "productId": "rv_4", "unitPrice": 35, "commission": 24.5, "totalPrice": 70, "discountedPrice": 35}],"total_amount":70.00,"total_commission":24.50,"ledger_amount":45.50,"timestamp":"2026-03-04T21:05:22.077Z","created_at":"2026-03-04T21:05:23.604747+00:00","updated_at":"2026-03-04T21:05:23.604747+00:00"}, 
 {"id":"01159c24-616f-4702-b40d-b10281be47fa","employee_id":"emp_3","employee_name":"Rob","customer_type":"standard","items":[{"name": "Navy", "quantity": 2, "productId": "rv_3", "unitPrice": 35, "commission": 24.5, "totalPrice": 70, "discountedPrice": 35}, {"name": "Bolt-Action", "quantity": 1, "productId": "rf_3", "unitPrice": 75, "commission": 26.25, "totalPrice": 75, "discountedPrice": 75}],"total_amount":145.00,"total_commission":50.75,"ledger_amount":94.25,"timestamp":"2026-03-04T02:13:20.263Z","created_at":"2026-03-04T02:13:22.644597+00:00","updated_at":"2026-03-04T02:13:22.644597+00:00"}, 
 {"id":"ae468ffd-881e-4693-acae-936484f191c8","employee_id":"emp_3","employee_name":"Rob","customer_type":"standard","items":[{"name": "Sawn-Off", "quantity": 2, "productId": "sg_1", "unitPrice": 35, "commission": 24.5, "totalPrice": 70, "discountedPrice": 35}],"total_amount":70.00,"total_commission":24.50,"ledger_amount":45.50,"timestamp":"2026-03-04T00:49:54.117Z","created_at":"2026-03-04T00:49:56.279613+00:00","updated_at":"2026-03-04T00:49:56.279613+00:00"}, 
 {"id":"d097b39a-98a4-4740-85c3-d82644beaaf4","employee_id":"emp_3","employee_name":"Rob","customer_type":"standard","items":[{"name": "Double Barrel", "quantity": 1, "productId": "sg_2", "unitPrice": 45, "commission": 15.749999999999998, "totalPrice": 45, "discountedPrice": 45}],"total_amount":45.00,"total_commission":15.75,"ledger_amount":29.25,"timestamp":"2026-03-02T23:11:44.496Z","created_at":"2026-03-02T23:11:45.563721+00:00","updated_at":"2026-03-02T23:11:45.563721+00:00"}, 
 {"id":"d8812887-02b6-427f-b85e-ada6bf36dd61","employee_id":"emp_1","employee_name":"Cat","customer_type":"standard","items":[{"name": "Semi-Auto", "quantity": 1, "productId": "pi_3", "unitPrice": 35, "commission": 12.25, "totalPrice": 35, "discountedPrice": 35}, {"name": "Navy", "quantity": 2, "productId": "rv_3", "unitPrice": 35, "commission": 24.5, "totalPrice": 70, "discountedPrice": 35}],"total_amount":105.00,"total_commission":36.75,"ledger_amount":68.25,"timestamp":"2026-03-02T21:38:03.155Z","created_at":"2026-03-02T21:38:15.639394+00:00","updated_at":"2026-03-02T21:38:15.639394+00:00"}, 
 {"id":"cdb74841-c2c3-49d5-9739-6fdc6a4a5647","employee_id":"emp_1","employee_name":"Cat","customer_type":"standard","items":[{"name": "Carcano", "quantity": 1, "productId": "rf_10", "unitPrice": 1000, "commission": 350, "totalPrice": 1000, "discountedPrice": 1000}],"total_amount":1000.00,"total_commission":350.00,"ledger_amount":650.00,"timestamp":"2026-03-02T02:54:33.919Z","created_at":"2026-03-02T02:54:45.863972+00:00","updated_at":"2026-03-02T02:54:45.863972+00:00"}, 
 {"id":"824e841a-52c7-42b0-9d69-aa56e93228af","employee_id":"emp_1","employee_name":"Cat","customer_type":"standard","items":[{"name": "Pump-Action", "quantity": 1, "productId": "sg_5", "unitPrice": 75, "commission": 26.25, "totalPrice": 75, "discountedPrice": 75}],"total_amount":75.00,"total_commission":26.25,"ledger_amount":48.75,"timestamp":"2026-03-02T02:35:50.534Z","created_at":"2026-03-02T02:36:01.626253+00:00","updated_at":"2026-03-02T02:36:01.626253+00:00"}, 
 {"id":"2021c34b-0c36-43d5-9f0f-3310ea4c6273","employee_id":"emp_1","employee_name":"Cat","customer_type":"standard","items":[{"name": "Winchester", "quantity": 1, "productId": "rp_3", "unitPrice": 55, "commission": 19.25, "totalPrice": 55, "discountedPrice": 55}, {"name": "Sawn-Off", "quantity": 2, "productId": "sg_1", "unitPrice": 35, "commission": 24.5, "totalPrice": 70, "discountedPrice": 35}],"total_amount":125.00,"total_commission":43.75,"ledger_amount":81.25,"timestamp":"2026-03-02T02:05:15.355Z","created_at":"2026-03-02T02:05:27.061972+00:00","updated_at":"2026-03-02T02:05:27.061972+00:00"}, 
 {"id":"9817ef30-9dd2-4dac-a5b0-50e341a776a2","employee_id":"emp_1","employee_name":"Cat","customer_type":"standard","items":[{"name": "Winchester", "quantity": 1, "productId": "rp_3", "unitPrice": 55, "commission": 19.25, "totalPrice": 55, "discountedPrice": 55}],"total_amount":55.00,"total_commission":19.25,"ledger_amount":35.75,"timestamp":"2026-02-27T00:02:24.526Z","created_at":"2026-02-27T00:02:30.411993+00:00","updated_at":"2026-02-27T00:02:30.411993+00:00"}, 
 {"id":"6ef28666-9eea-47fe-be2e-1805e0b7a150","employee_id":"emp_mlx7pd1m_caf25n","employee_name":"Mateo","customer_type":"standard","items":[{"name": "Navy", "quantity": 1, "productId": "rv_3", "unitPrice": 35, "commission": 12.25, "totalPrice": 35, "discountedPrice": 35}, {"name": "Pistol Ammo", "quantity": 1, "productId": "co_2", "unitPrice": 3, "commission": 1.0499999999999998, "totalPrice": 3, "discountedPrice": 3}],"total_amount":38.00,"total_commission":13.30,"ledger_amount":24.70,"timestamp":"2026-02-26T05:39:58.698Z","created_at":"2026-02-26T05:39:59.842261+00:00","updated_at":"2026-02-26T05:39:59.842261+00:00"}, 
 {"id":"ed13c9e6-6525-4b62-b089-0c7bb686f7f2","employee_id":"emp_mlx7pd1m_caf25n","employee_name":"Mateo","customer_type":"law_doc","items":[{"name": "Exotic Double", "quantity": 1, "productId": "sg_7", "unitPrice": 400, "commission": 125.99999999999999, "totalPrice": 360, "discountedPrice": 360}],"total_amount":360.00,"total_commission":126.00,"ledger_amount":234.00,"timestamp":"2026-02-26T04:55:17.756Z","created_at":"2026-02-26T04:55:19.314101+00:00","updated_at":"2026-02-26T04:55:19.314101+00:00"}, 
 {"id":"47c828b4-ae32-424b-9d56-62be5e92b755","employee_id":"emp_1","employee_name":"Cat","customer_type":"standard","items":[{"name": "Navy", "quantity": 1, "productId": "rv_3", "unitPrice": 35, "commission": 12.25, "totalPrice": 35, "discountedPrice": 35}],"total_amount":35.00,"total_commission":12.25,"ledger_amount":22.75,"timestamp":"2026-02-26T03:25:20.203Z","created_at":"2026-02-26T03:25:24.122473+00:00","updated_at":"2026-02-26T03:25:24.122473+00:00"}, 
 {"id":"4bf64003-2919-48dd-abb1-4ed912c9de7c","employee_id":"emp_1","employee_name":"Cat","customer_type":"standard","items":[{"name": "Schofield", "quantity": 2, "productId": "rv_1", "unitPrice": 10, "commission": 7, "totalPrice": 20, "discountedPrice": 10}],"total_amount":20.00,"total_commission":7.00,"ledger_amount":13.00,"timestamp":"2026-02-26T02:12:22.674Z","created_at":"2026-02-26T02:12:26.30342+00:00","updated_at":"2026-02-26T02:12:26.30342+00:00"}, 
 {"id":"4824a413-a425-4d7f-8fad-d3069e248829","employee_id":"emp_1","employee_name":"Cat","customer_type":"standard","items":[{"name": "Gewehr 98", "quantity": 1, "productId": "rf_5", "unitPrice": 400, "commission": 140, "totalPrice": 400, "discountedPrice": 400}],"total_amount":400.00,"total_commission":140.00,"ledger_amount":260.00,"timestamp":"2026-02-26T01:36:12.704Z","created_at":"2026-02-26T01:36:16.580925+00:00","updated_at":"2026-02-26T01:36:16.580925+00:00"}, 
 {"id":"9aad1b7d-7472-4a63-8cb4-95941f546546","employee_id":"emp_1","employee_name":"Cat","customer_type":"standard","items":[{"name": "Winchester", "quantity": 1, "productId": "rp_3", "unitPrice": 55, "commission": 19.25, "totalPrice": 55, "discountedPrice": 55}],"total_amount":55.00,"total_commission":19.25,"ledger_amount":35.75,"timestamp":"2026-02-25T22:56:56.758Z","created_at":"2026-02-25T22:57:00.839956+00:00","updated_at":"2026-02-25T22:57:00.839956+00:00"}, 
 {"id":"0f0cffad-acf5-4209-8960-b134b0f099f6","employee_id":"emp_1","employee_name":"Cat","customer_type":"standard","items":[{"name": "Bolt-Action", "quantity": 1, "productId": "rf_3", "unitPrice": 75, "commission": 26.25, "totalPrice": 75, "discountedPrice": 75}, {"name": "Engraving Plate", "quantity": 1, "productId": "co_5", "unitPrice": 20, "commission": 7, "totalPrice": 20, "discountedPrice": 20}],"total_amount":95.00,"total_commission":33.25,"ledger_amount":61.75,"timestamp":"2026-02-25T21:24:08.025Z","created_at":"2026-02-25T21:24:12.114136+00:00","updated_at":"2026-02-25T21:24:12.114136+00:00"}, 
 {"id":"f7b7fbd6-3bf7-42be-9306-b68b096dba3f","employee_id":"emp_1","employee_name":"Cat","customer_type":"law_doc","items":[{"name": "Henry", "quantity": 1, "productId": "rp_5", "unitPrice": 370, "commission": 116.55, "totalPrice": 333, "discountedPrice": 333}],"total_amount":333.00,"total_commission":116.55,"ledger_amount":216.45,"timestamp":"2026-02-25T20:14:21.957Z","created_at":"2026-02-25T20:14:25.630914+00:00","updated_at":"2026-02-25T20:14:25.630914+00:00"}, 
 {"id":"ef18b002-9c4a-487c-bafa-d2a4aa860cda","employee_id":"emp_1","employee_name":"Cat","customer_type":"law_doc","items":[{"name": "44 Model 1875", "quantity": 1, "productId": "rv_5", "unitPrice": 330, "commission": 103.94999999999999, "totalPrice": 297, "discountedPrice": 297}],"total_amount":297.00,"total_commission":103.95,"ledger_amount":193.05,"timestamp":"2026-02-25T02:12:10.065Z","created_at":"2026-02-25T02:12:10.394489+00:00","updated_at":"2026-02-25T02:12:10.394489+00:00"}, 
 {"id":"83e1e836-b1ee-4420-8ae8-db77df9349a9","employee_id":"emp_3","employee_name":"Rob","customer_type":"standard","items":[{"name": "LeMat", "quantity": 1, "productId": "rv_4", "unitPrice": 35, "commission": 12.25, "totalPrice": 35, "discountedPrice": 35}, {"name": "Engraving Plate", "quantity": 1, "productId": "co_5", "unitPrice": 20, "commission": 7, "totalPrice": 20, "discountedPrice": 20}],"total_amount":55.00,"total_commission":19.25,"ledger_amount":35.75,"timestamp":"2026-02-25T01:57:25.263Z","created_at":"2026-02-25T01:57:27.536058+00:00","updated_at":"2026-02-25T01:57:27.536058+00:00"}, 
 {"id":"2886583c-2ce1-4089-960d-48de56e6256b","employee_id":"emp_1","employee_name":"Cat","customer_type":"standard","items":[{"name": "Henry", "quantity": 1, "productId": "rp_5", "unitPrice": 370, "commission": 129.5, "totalPrice": 370, "discountedPrice": 370}],"total_amount":370.00,"total_commission":129.50,"ledger_amount":240.50,"timestamp":"2026-02-25T01:21:23.992Z","created_at":"2026-02-25T01:21:23.789105+00:00","updated_at":"2026-02-25T01:21:23.789105+00:00"}, 
 {"id":"5853e5ac-e0a2-4cdf-a552-57dfa9adf9e0","employee_id":"emp_1","employee_name":"Cat","customer_type":"standard","items":[{"name": "Bolt-Action", "quantity": 1, "productId": "rf_3", "unitPrice": 75, "commission": 26.25, "totalPrice": 75, "discountedPrice": 75}],"total_amount":75.00,"total_commission":26.25,"ledger_amount":48.75,"timestamp":"2026-02-24T21:03:09.613Z","created_at":"2026-02-24T21:03:11.850884+00:00","updated_at":"2026-02-24T21:03:11.850884+00:00"}, 
 {"id":"71e3ae40-230e-425d-865f-2e12930caba5","employee_id":"emp_4","employee_name":"Morris","customer_type":"standard","items":[{"name": "Luger", "quantity": 1, "productId": "pi_5", "unitPrice": 350, "commission": 122.49999999999999, "totalPrice": 350, "discountedPrice": 350}],"total_amount":350.00,"total_commission":122.50,"ledger_amount":227.50,"timestamp":"2026-02-24T20:24:43.592Z","created_at":"2026-02-24T20:24:44.068408+00:00","updated_at":"2026-02-24T20:24:44.068408+00:00"}, 
 {"id":"8ec005c0-76d8-402d-9739-81f5f1f9e65e","employee_id":"emp_mlx7pd1m_caf25n","employee_name":"Mateo","customer_type":"standard","items":[{"name": "Pistol Ammo", "quantity": 10, "productId": "co_2", "unitPrice": 3, "commission": 10.5, "totalPrice": 30, "discountedPrice": 3}],"total_amount":30.00,"total_commission":10.50,"ledger_amount":19.50,"timestamp":"2026-02-24T02:41:11.011Z","created_at":"2026-02-24T02:41:11.331424+00:00","updated_at":"2026-02-24T02:41:11.331424+00:00"}, 
 {"id":"b1a96ae9-c796-4702-aa06-e909cdbb8b26","employee_id":"emp_mlx7pd1m_caf25n","employee_name":"Mateo","customer_type":"standard","items":[{"name": "Pistol Ammo", "quantity": 6, "productId": "co_2", "unitPrice": 3, "commission": 6.3, "totalPrice": 18, "discountedPrice": 3}],"total_amount":18.00,"total_commission":6.30,"ledger_amount":11.70,"timestamp":"2026-02-24T02:19:48.425Z","created_at":"2026-02-24T02:19:48.823047+00:00","updated_at":"2026-02-24T02:19:48.823047+00:00"}, 
 {"id":"329a3e57-0c41-495c-845f-f966a0ba950e","employee_id":"emp_mlx7pd1m_caf25n","employee_name":"Mateo","customer_type":"standard","items":[{"name": "Mauser", "quantity": 2, "productId": "pi_2", "unitPrice": 35, "commission": 24.5, "totalPrice": 70, "discountedPrice": 35}, {"name": "Bolt-Action", "quantity": 1, "productId": "rf_3", "unitPrice": 75, "commission": 26.25, "totalPrice": 75, "discountedPrice": 75}],"total_amount":145.00,"total_commission":50.75,"ledger_amount":94.25,"timestamp":"2026-02-24T02:12:57.063Z","created_at":"2026-02-24T02:12:57.644384+00:00","updated_at":"2026-02-24T02:12:57.644384+00:00"}, 
 {"id":"807c9610-da4e-4985-ae11-24e61e068a97","employee_id":"emp_1","employee_name":"Cat","customer_type":"standard","items":[{"name": "Pump-Action", "quantity": 1, "productId": "sg_5", "unitPrice": 75, "commission": 26.25, "totalPrice": 75, "discountedPrice": 75}],"total_amount":75.00,"total_commission":26.25,"ledger_amount":48.75,"timestamp":"2026-02-23T21:11:29.103Z","created_at":"2026-02-23T21:11:29.83717+00:00","updated_at":"2026-02-23T21:11:29.83717+00:00"}, 
 {"id":"bb989a56-73b2-4210-a701-f8aa4107cf9f","employee_id":"emp_1","employee_name":"Cat","customer_type":"standard","items":[{"name": "LeMat", "quantity": 2, "productId": "rv_4", "unitPrice": 35, "commission": 24.5, "totalPrice": 70, "discountedPrice": 35}],"total_amount":70.00,"total_commission":24.50,"ledger_amount":45.50,"timestamp":"2026-02-23T20:39:25.540Z","created_at":"2026-02-23T20:39:25.641355+00:00","updated_at":"2026-02-23T20:39:25.641355+00:00"}, 
 {"id":"c1a65700-4cfa-41b0-9935-f98260d48f4d","employee_id":"emp_1","employee_name":"Cat","customer_type":"standard","items":[{"name": "Semi-Auto", "quantity": 2, "productId": "pi_3", "unitPrice": 35, "commission": 24.5, "totalPrice": 70, "discountedPrice": 35}],"total_amount":70.00,"total_commission":24.50,"ledger_amount":45.50,"timestamp":"2026-02-23T20:06:12.820Z","created_at":"2026-02-23T20:06:12.942022+00:00","updated_at":"2026-02-23T20:06:12.942022+00:00"}, 
 {"id":"e8900c1b-57cb-45dc-a835-4b17839fa34b","employee_id":"emp_1","employee_name":"Cat","customer_type":"standard","items":[{"name": "Gun Oil", "quantity": 100, "productId": "co_1", "unitPrice": 0.5, "commission": 17.5, "totalPrice": 50, "discountedPrice": 0.5}, {"name": "Pistol Ammo", "quantity": 100, "productId": "co_2", "unitPrice": 3, "commission": 105, "totalPrice": 300, "discountedPrice": 3}],"total_amount":350.00,"total_commission":122.50,"ledger_amount":227.50,"timestamp":"2026-02-22T23:57:17.416Z","created_at":"2026-02-22T23:58:29.473066+00:00","updated_at":"2026-02-22T23:58:29.473066+00:00"}, 
 {"id":"ab32c051-d63b-48f5-9586-d75cd7183e07","employee_id":"emp_1","employee_name":"Cat","customer_type":"standard","items":[{"name": "Navy", "quantity": 1, "productId": "rv_3", "unitPrice": 35, "commission": 12.25, "totalPrice": 35, "discountedPrice": 35}, {"name": "Bolt-Action", "quantity": 1, "productId": "rf_3", "unitPrice": 75, "commission": 26.25, "totalPrice": 75, "discountedPrice": 75}],"total_amount":110.00,"total_commission":38.50,"ledger_amount":71.50,"timestamp":"2026-02-22T21:25:24.873Z","created_at":"2026-02-22T21:26:36.712417+00:00","updated_at":"2026-02-22T21:26:36.712417+00:00"}, 
 {"id":"e168e255-1116-4225-a5aa-c7686005bce8","employee_id":"emp_mlx7pd1m_caf25n","employee_name":"Mateo","customer_type":"standard","items":[{"name": "Gun Oil", "quantity": 3, "productId": "co_1", "unitPrice": 0.5, "commission": 0.375, "totalPrice": 1.5, "discountedPrice": 0.5}],"total_amount":1.50,"total_commission":0.38,"ledger_amount":1.13,"timestamp":"2026-02-22T05:02:41.395Z","created_at":"2026-02-22T05:02:41.926527+00:00","updated_at":"2026-02-22T05:02:41.926527+00:00"}, 
 {"id":"a6d828a0-b485-4187-867f-e00cddf04f9d","employee_id":"emp_1","employee_name":"Cat","customer_type":"standard","items":[{"name": "Colt 1911", "quantity": 1, "productId": "pi_1", "unitPrice": 450, "commission": 112.5, "totalPrice": 450, "discountedPrice": 450}, {"name": "Pistol Ammo", "quantity": 11, "productId": "co_2", "unitPrice": 3, "commission": 8.25, "totalPrice": 33, "discountedPrice": 3}],"total_amount":483.00,"total_commission":120.75,"ledger_amount":362.25,"timestamp":"2026-02-21T06:00:46.282Z","created_at":"2026-02-21T06:01:53.526519+00:00","updated_at":"2026-02-21T06:01:53.526519+00:00"}, 
 {"id":"551a2eb7-2a82-479e-8208-a9e0e44f7c49","employee_id":"emp_1","employee_name":"Cat","customer_type":"standard","items":[{"name": "Colt 1911", "quantity": 1, "productId": "pi_1", "unitPrice": 450, "commission": 112.5, "totalPrice": 450, "discountedPrice": 450}],"total_amount":450.00,"total_commission":112.50,"ledger_amount":337.50,"timestamp":"2026-02-21T05:05:07.509Z","created_at":"2026-02-21T05:06:14.771461+00:00","updated_at":"2026-02-21T05:06:14.771461+00:00"}, 
 {"id":"d174ef24-3423-4ec2-b498-1057afe8d2de","employee_id":"emp_1","employee_name":"Cat","customer_type":"standard","items":[{"name": "Sawn-Off", "quantity": 1, "productId": "sg_1", "unitPrice": 35, "commission": 8.75, "totalPrice": 35, "discountedPrice": 35}, {"name": "Navy", "quantity": 1, "productId": "rv_3", "unitPrice": 35, "commission": 8.75, "totalPrice": 35, "discountedPrice": 35}],"total_amount":70.00,"total_commission":17.50,"ledger_amount":52.50,"timestamp":"2026-02-21T05:05:01.211Z","created_at":"2026-02-21T05:06:09.40069+00:00","updated_at":"2026-02-21T05:06:09.40069+00:00"}, 
 {"id":"66ac46d8-8231-4551-9fe5-c8719ec5c418","employee_id":"emp_1","employee_name":"Cat","customer_type":"standard","items":[{"name": "Winchester", "quantity": 1, "productId": "rp_3", "unitPrice": 55, "commission": 13.75, "totalPrice": 55, "discountedPrice": 55}],"total_amount":55.00,"total_commission":13.75,"ledger_amount":41.25,"timestamp":"2026-02-20T20:45:19.046Z","created_at":"2026-02-20T20:46:26.65585+00:00","updated_at":"2026-02-20T20:46:26.65585+00:00"}, 
 {"id":"1e3ce995-093b-4633-97e0-af8656b5427f","employee_id":"emp_1","employee_name":"Cat","customer_type":"standard","items":[{"name": "Carcano", "quantity": 1, "productId": "rf_10", "unitPrice": 1000, "commission": 250, "totalPrice": 1000, "discountedPrice": 1000}, {"name": "Engraving Plate", "quantity": 1, "productId": "co_5", "unitPrice": 20, "commission": 5, "totalPrice": 20, "discountedPrice": 20}],"total_amount":1020.00,"total_commission":255.00,"ledger_amount":765.00,"timestamp":"2026-02-19T23:17:00.793Z","created_at":"2026-02-19T23:18:05.624563+00:00","updated_at":"2026-02-19T23:18:05.624563+00:00"}, 
 {"id":"2cd30a50-8299-4e94-bc5b-5927e0aef6bc","employee_id":"emp_4","employee_name":"Morris","customer_type":"standard","items":[{"name": "Navy", "quantity": 2, "productId": "rv_3", "unitPrice": 35, "commission": 17.5, "totalPrice": 70, "discountedPrice": 35}],"total_amount":70.00,"total_commission":17.50,"ledger_amount":52.50,"timestamp":"2026-02-19T20:57:27.440Z","created_at":"2026-02-19T20:58:32.676028+00:00","updated_at":"2026-02-19T20:58:32.676028+00:00"}, 
 {"id":"78dd1b4d-0fb0-4ca9-8cae-ab3141c8759a","employee_id":"emp_1","employee_name":"Cat","customer_type":"standard","items":[{"name": "Henry", "quantity": 1, "productId": "rp_5", "unitPrice": 370, "commission": 92.5, "totalPrice": 370, "discountedPrice": 370}],"total_amount":370.00,"total_commission":92.50,"ledger_amount":277.50,"timestamp":"2026-02-19T19:43:04.445Z","created_at":"2026-02-19T19:44:10.285221+00:00","updated_at":"2026-02-19T19:44:10.285221+00:00"}, 
 {"id":"464fe0e8-6420-4b0a-8596-5160b26204ac","employee_id":"emp_1","employee_name":"Cat","customer_type":"standard","items":[{"name": "Cattleman", "quantity": 1, "productId": "rv_9", "unitPrice": 5, "commission": 1.25, "totalPrice": 5, "discountedPrice": 5}, {"name": "Evans", "quantity": 1, "productId": "rp_1", "unitPrice": 25, "commission": 6.25, "totalPrice": 25, "discountedPrice": 25}],"total_amount":30.00,"total_commission":7.50,"ledger_amount":22.50,"timestamp":"2026-02-19T18:34:24.293Z","created_at":"2026-02-19T18:35:29.847456+00:00","updated_at":"2026-02-19T18:35:29.847456+00:00"}, 
 {"id":"2c096e03-624f-42fd-8f6d-26ef91d09992","employee_id":"emp_3","employee_name":"Rob","customer_type":"standard","items":[{"name": "Henry", "quantity": 1, "productId": "rp_5", "unitPrice": 370, "commission": 92.5, "totalPrice": 370, "discountedPrice": 370}],"total_amount":370.00,"total_commission":92.50,"ledger_amount":277.50,"timestamp":"2026-02-18T01:00:11.801Z","created_at":"2026-02-18T01:01:12.778475+00:00","updated_at":"2026-02-18T01:01:12.778475+00:00"}, 
 {"id":"d6068f77-165c-4048-9049-c729ca13d53c","employee_id":"emp_1","employee_name":"Cat","customer_type":"standard","items":[{"name": "Engraving Plate", "quantity": 3, "productId": "co_5", "unitPrice": 20, "commission": 15, "totalPrice": 60, "discountedPrice": 20}, {"name": "Carcano", "quantity": 2, "productId": "rf_10", "unitPrice": 1000, "commission": 500, "totalPrice": 2000, "discountedPrice": 1000}],"total_amount":2060.00,"total_commission":515.00,"ledger_amount":1545.00,"timestamp":"2026-02-17T20:50:36.550Z","created_at":"2026-02-17T20:51:37.843215+00:00","updated_at":"2026-02-17T20:51:37.843215+00:00"}, 
 {"id":"a590faf6-5128-42bb-b47e-98809596ea8b","employee_id":"emp_1","employee_name":"Cat","customer_type":"standard","items":[{"name": "Winchester", "quantity": 1, "productId": "rp_3", "unitPrice": 55, "commission": 13.75, "totalPrice": 55, "discountedPrice": 55}],"total_amount":55.00,"total_commission":13.75,"ledger_amount":41.25,"timestamp":"2026-02-16T22:16:39.184Z","created_at":"2026-02-16T22:17:39.163808+00:00","updated_at":"2026-02-16T22:17:39.163808+00:00"}, 
 {"id":"d8ce984c-745f-4ee6-adf5-44257967bd23","employee_id":"emp_1","employee_name":"Cat","customer_type":"standard","items":[{"name": "Pistol Ammo", "quantity": 10, "productId": "co_2", "unitPrice": 3, "commission": 7.5, "totalPrice": 30, "discountedPrice": 3}],"total_amount":30.00,"total_commission":7.50,"ledger_amount":22.50,"timestamp":"2026-02-16T22:06:24.974Z","created_at":"2026-02-16T22:07:24.750843+00:00","updated_at":"2026-02-16T22:07:24.750843+00:00"}, 
 {"id":"ba7d828c-0139-4f77-aed4-2a869ce5a885","employee_id":"emp_4","employee_name":"Morris","customer_type":"standard","items":[{"name": "Gun Oil", "quantity": 10, "productId": "co_1", "unitPrice": 0.5, "commission": 1.25, "totalPrice": 5, "discountedPrice": 0.5}],"total_amount":5.00,"total_commission":1.25,"ledger_amount":3.75,"timestamp":"2026-02-15T05:48:41.354Z","created_at":"2026-02-15T05:48:38.292775+00:00","updated_at":"2026-02-15T05:48:38.292775+00:00"}, 
 {"id":"1be00ebd-ab5d-448d-8861-d414b61cf714","employee_id":"emp_4","employee_name":"Morris","customer_type":"standard","items":[{"name": "Semi-Auto", "quantity": 1, "productId": "pi_3", "unitPrice": 35, "commission": 8.75, "totalPrice": 35, "discountedPrice": 35}],"total_amount":35.00,"total_commission":8.75,"ledger_amount":26.25,"timestamp":"2026-02-15T05:36:40.453Z","created_at":"2026-02-15T05:36:37.490101+00:00","updated_at":"2026-02-15T05:36:37.490101+00:00"}, 
 {"id":"01b52e12-d485-43d9-ae60-1829681c8ab6","employee_id":"emp_1","employee_name":"Cat","customer_type":"standard","items":[{"name": "Pistol Ammo", "quantity": 3, "productId": "co_2", "unitPrice": 3, "commission": 2.25, "totalPrice": 9, "discountedPrice": 3}, {"name": "Gun Oil", "quantity": 4, "productId": "co_1", "unitPrice": 0.5, "commission": 0.5, "totalPrice": 2, "discountedPrice": 0.5}],"total_amount":11.00,"total_commission":2.75,"ledger_amount":8.25,"timestamp":"2026-02-14T00:40:11.954Z","created_at":"2026-02-14T00:41:05.922072+00:00","updated_at":"2026-02-14T00:41:05.922072+00:00"}, 
 {"id":"cfb60865-7b36-40d9-95a3-5fa5f6ad1161","employee_id":"emp_1","employee_name":"Cat","customer_type":"standard","items":[{"name": "Mauser", "quantity": 2, "productId": "pi_2", "unitPrice": 35, "commission": 17.5, "totalPrice": 70, "discountedPrice": 35}],"total_amount":70.00,"total_commission":17.50,"ledger_amount":52.50,"timestamp":"2026-02-14T00:31:13.739Z","created_at":"2026-02-14T00:32:07.503766+00:00","updated_at":"2026-02-14T00:32:07.503766+00:00"}, 
 {"id":"cd71dc0d-0653-4736-9be6-95366e249b46","employee_id":"emp_1","employee_name":"Cat","customer_type":"standard","items":[{"name": "Navy", "quantity": 1, "productId": "rv_3", "unitPrice": 35, "commission": 8.75, "totalPrice": 35, "discountedPrice": 35}, {"name": "Evans", "quantity": 1, "productId": "rp_1", "unitPrice": 25, "commission": 6.25, "totalPrice": 25, "discountedPrice": 25}],"total_amount":60.00,"total_commission":15.00,"ledger_amount":45.00,"timestamp":"2026-02-14T00:12:28.939Z","created_at":"2026-02-14T00:13:22.754953+00:00","updated_at":"2026-02-14T00:13:22.754953+00:00"}]